{
  "metadata" : {
    "identifier" : "https://www.nettruyenio.com/truyen-tranh/ranh-gioi-quy-127040",
    "title" : "Ranh Giới Quỷ - Chapter 30",
    "subtitle" : null,
    "author" : null,
    "narrator" : null,
    "language" : "vi",
    "description" : null,
    "publisher" : "N/A",
    "subject" : null,
    "modified" : null,
    "published" : "2023-08-07",
    "duration" : 0,
    "abridged" : false,
    "conformsTo" : "https://readium.org/webpub-manifest/profiles/divina",
    "numberOfPages" : 33,
    "readingProgression" : "ttb",
    "belongsTo" : null,
    "presentation" : {
      "fit" : "width",
      "overflow" : "scrolled",
      "continuous" : true
    },
    "@type" : null,
    "schema:license" : null
  },
  "links" : [ {
    "rel" : "self",
    "href" : "https://raw.githubusercontent.com/thuvienonline40/book_storage_collection/main/comic_manifest.json",
    "type" : "application/divina+json"
  } ],
  "readingOrder" : [ {
    "href" : "https://raw.githubusercontent.com/duyhuynh652018/comic_storage6/main/IMAGE/IMAGE_a16de96f6d95f6b550cfe035801173cc_7cc6d3e70ce85877e76dd99ea7153780_7ab4f93a2e03afafe3a755f2db277805.jpg",
    "type" : "image/jpeg",
    "bitrate" : 0,
    "duration" : 0,
    "title" : null,
    "properties" : null,
    "alternate" : [ {
      "href" : "https://i334.ntcdntempv3.com/data/images/12704/437739/001-fix.jpg?data=net",
      "type" : "image/jpeg",
      "bitrate" : 0,
      "duration" : 0,
      "title" : null,
      "properties" : null,
      "alternate" : null
    } ]
  }, {
    "href" : "https://raw.githubusercontent.com/duyhuynh652018/comic_storage6/main/IMAGE/IMAGE_a16de96f6d95f6b550cfe035801173cc_7cc6d3e70ce85877e76dd99ea7153780_22f05d51580040f29574b7825accdf4f.jpg",
    "type" : "image/jpeg",
    "bitrate" : 0,
    "duration" : 0,
    "title" : null,
    "properties" : null,
    "alternate" : [ {
      "href" : "https://i334.ntcdntempv3.com/data/images/12704/437739/002-fix.jpg?data=net",
      "type" : "image/jpeg",
      "bitrate" : 0,
      "duration" : 0,
      "title" : null,
      "properties" : null,
      "alternate" : null
    } ]
  }, {
    "href" : "https://raw.githubusercontent.com/duyhuynh652018/comic_storage6/main/IMAGE/IMAGE_a16de96f6d95f6b550cfe035801173cc_7cc6d3e70ce85877e76dd99ea7153780_6b43e532c6aee426a30b45f52e9958b4.jpg",
    "type" : "image/jpeg",
    "bitrate" : 0,
    "duration" : 0,
    "title" : null,
    "properties" : null,
    "alternate" : [ {
      "href" : "https://i334.ntcdntempv3.com/data/images/12704/437739/003-fix.jpg?data=net",
      "type" : "image/jpeg",
      "bitrate" : 0,
      "duration" : 0,
      "title" : null,
      "properties" : null,
      "alternate" : null
    } ]
  }, {
    "href" : "https://raw.githubusercontent.com/duyhuynh652018/comic_storage6/main/IMAGE/IMAGE_a16de96f6d95f6b550cfe035801173cc_7cc6d3e70ce85877e76dd99ea7153780_187cd8eeebb15e59fca7909750985a60.jpg",
    "type" : "image/jpeg",
    "bitrate" : 0,
    "duration" : 0,
    "title" : null,
    "properties" : null,
    "alternate" : [ {
      "href" : "https://i334.ntcdntempv3.com/data/images/12704/437739/004-fix.jpg?data=net",
      "type" : "image/jpeg",
      "bitrate" : 0,
      "duration" : 0,
      "title" : null,
      "properties" : null,
      "alternate" : null
    } ]
  }, {
    "href" : "https://raw.githubusercontent.com/duyhuynh652018/comic_storage6/main/IMAGE/IMAGE_a16de96f6d95f6b550cfe035801173cc_7cc6d3e70ce85877e76dd99ea7153780_ed9467b0b07612222a615d42b7ee0cb5.jpg",
    "type" : "image/jpeg",
    "bitrate" : 0,
    "duration" : 0,
    "title" : null,
    "properties" : null,
    "alternate" : [ {
      "href" : "https://i334.ntcdntempv3.com/data/images/12704/437739/005-fix.jpg?data=net",
      "type" : "image/jpeg",
      "bitrate" : 0,
      "duration" : 0,
      "title" : null,
      "properties" : null,
      "alternate" : null
    } ]
  }, {
    "href" : "https://raw.githubusercontent.com/duyhuynh652018/comic_storage6/main/IMAGE/IMAGE_a16de96f6d95f6b550cfe035801173cc_7cc6d3e70ce85877e76dd99ea7153780_8bbc924fd65ceb07a036f8371f040fa8.jpg",
    "type" : "image/jpeg",
    "bitrate" : 0,
    "duration" : 0,
    "title" : null,
    "properties" : null,
    "alternate" : [ {
      "href" : "https://i334.ntcdntempv3.com/data/images/12704/437739/006-fix.jpg?data=net",
      "type" : "image/jpeg",
      "bitrate" : 0,
      "duration" : 0,
      "title" : null,
      "properties" : null,
      "alternate" : null
    } ]
  }, {
    "href" : "https://raw.githubusercontent.com/duyhuynh652018/comic_storage6/main/IMAGE/IMAGE_a16de96f6d95f6b550cfe035801173cc_7cc6d3e70ce85877e76dd99ea7153780_b578ea77e1b6c8b486f4bc6607fc4bbf.jpg",
    "type" : "image/jpeg",
    "bitrate" : 0,
    "duration" : 0,
    "title" : null,
    "properties" : null,
    "alternate" : [ {
      "href" : "https://i334.ntcdntempv3.com/data/images/12704/437739/007-fix.jpg?data=net",
      "type" : "image/jpeg",
      "bitrate" : 0,
      "duration" : 0,
      "title" : null,
      "properties" : null,
      "alternate" : null
    } ]
  }, {
    "href" : "https://raw.githubusercontent.com/duyhuynh652018/comic_storage6/main/IMAGE/IMAGE_a16de96f6d95f6b550cfe035801173cc_7cc6d3e70ce85877e76dd99ea7153780_35fbbc019acea24e7739d25323f5dece.jpg",
    "type" : "image/jpeg",
    "bitrate" : 0,
    "duration" : 0,
    "title" : null,
    "properties" : null,
    "alternate" : [ {
      "href" : "https://i334.ntcdntempv3.com/data/images/12704/437739/008-fix.jpg?data=net",
      "type" : "image/jpeg",
      "bitrate" : 0,
      "duration" : 0,
      "title" : null,
      "properties" : null,
      "alternate" : null
    } ]
  }, {
    "href" : "https://raw.githubusercontent.com/duyhuynh652018/comic_storage6/main/IMAGE/IMAGE_a16de96f6d95f6b550cfe035801173cc_7cc6d3e70ce85877e76dd99ea7153780_c159510d4e87566d2a7ffc2a11116e4f.jpg",
    "type" : "image/jpeg",
    "bitrate" : 0,
    "duration" : 0,
    "title" : null,
    "properties" : null,
    "alternate" : [ {
      "href" : "https://i334.ntcdntempv3.com/data/images/12704/437739/009-fix.jpg?data=net",
      "type" : "image/jpeg",
      "bitrate" : 0,
      "duration" : 0,
      "title" : null,
      "properties" : null,
      "alternate" : null
    } ]
  }, {
    "href" : "https://raw.githubusercontent.com/duyhuynh652018/comic_storage6/main/IMAGE/IMAGE_a16de96f6d95f6b550cfe035801173cc_7cc6d3e70ce85877e76dd99ea7153780_b622bee45791dcec5d247112965d8239.jpg",
    "type" : "image/jpeg",
    "bitrate" : 0,
    "duration" : 0,
    "title" : null,
    "properties" : null,
    "alternate" : [ {
      "href" : "https://i334.ntcdntempv3.com/data/images/12704/437739/010-fix.jpg?data=net",
      "type" : "image/jpeg",
      "bitrate" : 0,
      "duration" : 0,
      "title" : null,
      "properties" : null,
      "alternate" : null
    } ]
  }, {
    "href" : "https://raw.githubusercontent.com/duyhuynh652018/comic_storage6/main/IMAGE/IMAGE_a16de96f6d95f6b550cfe035801173cc_7cc6d3e70ce85877e76dd99ea7153780_391f3da24a93e4d1a407e768d71a28fd.jpg",
    "type" : "image/jpeg",
    "bitrate" : 0,
    "duration" : 0,
    "title" : null,
    "properties" : null,
    "alternate" : [ {
      "href" : "https://i334.ntcdntempv3.com/data/images/12704/437739/011-fix.jpg?data=net",
      "type" : "image/jpeg",
      "bitrate" : 0,
      "duration" : 0,
      "title" : null,
      "properties" : null,
      "alternate" : null
    } ]
  }, {
    "href" : "https://raw.githubusercontent.com/duyhuynh652018/comic_storage6/main/IMAGE/IMAGE_a16de96f6d95f6b550cfe035801173cc_7cc6d3e70ce85877e76dd99ea7153780_000fde07a7eff1f6396e1a12452bb669.jpg",
    "type" : "image/jpeg",
    "bitrate" : 0,
    "duration" : 0,
    "title" : null,
    "properties" : null,
    "alternate" : [ {
      "href" : "https://i334.ntcdntempv3.com/data/images/12704/437739/012-fix.jpg?data=net",
      "type" : "image/jpeg",
      "bitrate" : 0,
      "duration" : 0,
      "title" : null,
      "properties" : null,
      "alternate" : null
    } ]
  }, {
    "href" : "https://raw.githubusercontent.com/duyhuynh652018/comic_storage6/main/IMAGE/IMAGE_a16de96f6d95f6b550cfe035801173cc_7cc6d3e70ce85877e76dd99ea7153780_12324f4cc18d99cab07e214263df8cf1.jpg",
    "type" : "image/jpeg",
    "bitrate" : 0,
    "duration" : 0,
    "title" : null,
    "properties" : null,
    "alternate" : [ {
      "href" : "https://i334.ntcdntempv3.com/data/images/12704/437739/013-fix.jpg?data=net",
      "type" : "image/jpeg",
      "bitrate" : 0,
      "duration" : 0,
      "title" : null,
      "properties" : null,
      "alternate" : null
    } ]
  }, {
    "href" : "https://raw.githubusercontent.com/duyhuynh652018/comic_storage6/main/IMAGE/IMAGE_a16de96f6d95f6b550cfe035801173cc_7cc6d3e70ce85877e76dd99ea7153780_7b557f029aed9fa3b91f94c234b4784b.jpg",
    "type" : "image/jpeg",
    "bitrate" : 0,
    "duration" : 0,
    "title" : null,
    "properties" : null,
    "alternate" : [ {
      "href" : "https://i334.ntcdntempv3.com/data/images/12704/437739/014-fix.jpg?data=net",
      "type" : "image/jpeg",
      "bitrate" : 0,
      "duration" : 0,
      "title" : null,
      "properties" : null,
      "alternate" : null
    } ]
  }, {
    "href" : "https://raw.githubusercontent.com/duyhuynh652018/comic_storage6/main/IMAGE/IMAGE_a16de96f6d95f6b550cfe035801173cc_7cc6d3e70ce85877e76dd99ea7153780_b8bced06c8106261e25d31024cde0432.jpg",
    "type" : "image/jpeg",
    "bitrate" : 0,
    "duration" : 0,
    "title" : null,
    "properties" : null,
    "alternate" : [ {
      "href" : "https://i334.ntcdntempv3.com/data/images/12704/437739/015-fix.jpg?data=net",
      "type" : "image/jpeg",
      "bitrate" : 0,
      "duration" : 0,
      "title" : null,
      "properties" : null,
      "alternate" : null
    } ]
  }, {
    "href" : "https://raw.githubusercontent.com/duyhuynh652018/comic_storage6/main/IMAGE/IMAGE_a16de96f6d95f6b550cfe035801173cc_7cc6d3e70ce85877e76dd99ea7153780_cf8985cee95d9d6e6eb0e43e0c83eeca.jpg",
    "type" : "image/jpeg",
    "bitrate" : 0,
    "duration" : 0,
    "title" : null,
    "properties" : null,
    "alternate" : [ {
      "href" : "https://i334.ntcdntempv3.com/data/images/12704/437739/016-fix.jpg?data=net",
      "type" : "image/jpeg",
      "bitrate" : 0,
      "duration" : 0,
      "title" : null,
      "properties" : null,
      "alternate" : null
    } ]
  }, {
    "href" : "https://raw.githubusercontent.com/duyhuynh652018/comic_storage6/main/IMAGE/IMAGE_a16de96f6d95f6b550cfe035801173cc_7cc6d3e70ce85877e76dd99ea7153780_1a20ceec65f778ae8cae88fb361c12dd.jpg",
    "type" : "image/jpeg",
    "bitrate" : 0,
    "duration" : 0,
    "title" : null,
    "properties" : null,
    "alternate" : [ {
      "href" : "https://i334.ntcdntempv3.com/data/images/12704/437739/017-fix.jpg?data=net",
      "type" : "image/jpeg",
      "bitrate" : 0,
      "duration" : 0,
      "title" : null,
      "properties" : null,
      "alternate" : null
    } ]
  }, {
    "href" : "https://raw.githubusercontent.com/duyhuynh652018/comic_storage6/main/IMAGE/IMAGE_a16de96f6d95f6b550cfe035801173cc_7cc6d3e70ce85877e76dd99ea7153780_a85b388211d11e9cd4622515a004c370.jpg",
    "type" : "image/jpeg",
    "bitrate" : 0,
    "duration" : 0,
    "title" : null,
    "properties" : null,
    "alternate" : [ {
      "href" : "https://i334.ntcdntempv3.com/data/images/12704/437739/018-fix.jpg?data=net",
      "type" : "image/jpeg",
      "bitrate" : 0,
      "duration" : 0,
      "title" : null,
      "properties" : null,
      "alternate" : null
    } ]
  }, {
    "href" : "https://raw.githubusercontent.com/duyhuynh652018/comic_storage6/main/IMAGE/IMAGE_a16de96f6d95f6b550cfe035801173cc_7cc6d3e70ce85877e76dd99ea7153780_74b8664816951c38a3ad0c79b7d7e96f.jpg",
    "type" : "image/jpeg",
    "bitrate" : 0,
    "duration" : 0,
    "title" : null,
    "properties" : null,
    "alternate" : [ {
      "href" : "https://i334.ntcdntempv3.com/data/images/12704/437739/019-fix.jpg?data=net",
      "type" : "image/jpeg",
      "bitrate" : 0,
      "duration" : 0,
      "title" : null,
      "properties" : null,
      "alternate" : null
    } ]
  }, {
    "href" : "https://raw.githubusercontent.com/duyhuynh652018/comic_storage6/main/IMAGE/IMAGE_a16de96f6d95f6b550cfe035801173cc_7cc6d3e70ce85877e76dd99ea7153780_c21d82bb30558fe572eb48613e9560ca.jpg",
    "type" : "image/jpeg",
    "bitrate" : 0,
    "duration" : 0,
    "title" : null,
    "properties" : null,
    "alternate" : [ {
      "href" : "https://i334.ntcdntempv3.com/data/images/12704/437739/020-fix.jpg?data=net",
      "type" : "image/jpeg",
      "bitrate" : 0,
      "duration" : 0,
      "title" : null,
      "properties" : null,
      "alternate" : null
    } ]
  }, {
    "href" : "https://raw.githubusercontent.com/duyhuynh652018/comic_storage6/main/IMAGE/IMAGE_a16de96f6d95f6b550cfe035801173cc_7cc6d3e70ce85877e76dd99ea7153780_b2d96445208700dd1c29a6a14a7b1488.jpg",
    "type" : "image/jpeg",
    "bitrate" : 0,
    "duration" : 0,
    "title" : null,
    "properties" : null,
    "alternate" : [ {
      "href" : "https://i334.ntcdntempv3.com/data/images/12704/437739/021-fix.jpg?data=net",
      "type" : "image/jpeg",
      "bitrate" : 0,
      "duration" : 0,
      "title" : null,
      "properties" : null,
      "alternate" : null
    } ]
  }, {
    "href" : "https://raw.githubusercontent.com/duyhuynh652018/comic_storage6/main/IMAGE/IMAGE_a16de96f6d95f6b550cfe035801173cc_7cc6d3e70ce85877e76dd99ea7153780_faf6f082dfbe75c2953bc0bd1b2fb44b.jpg",
    "type" : "image/jpeg",
    "bitrate" : 0,
    "duration" : 0,
    "title" : null,
    "properties" : null,
    "alternate" : [ {
      "href" : "https://i334.ntcdntempv3.com/data/images/12704/437739/022-fix.jpg?data=net",
      "type" : "image/jpeg",
      "bitrate" : 0,
      "duration" : 0,
      "title" : null,
      "properties" : null,
      "alternate" : null
    } ]
  }, {
    "href" : "https://raw.githubusercontent.com/duyhuynh652018/comic_storage6/main/IMAGE/IMAGE_a16de96f6d95f6b550cfe035801173cc_7cc6d3e70ce85877e76dd99ea7153780_d2fecd912901811b8ec6fc03f3415216.jpg",
    "type" : "image/jpeg",
    "bitrate" : 0,
    "duration" : 0,
    "title" : null,
    "properties" : null,
    "alternate" : [ {
      "href" : "https://i334.ntcdntempv3.com/data/images/12704/437739/023-fix.jpg?data=net",
      "type" : "image/jpeg",
      "bitrate" : 0,
      "duration" : 0,
      "title" : null,
      "properties" : null,
      "alternate" : null
    } ]
  }, {
    "href" : "https://raw.githubusercontent.com/duyhuynh652018/comic_storage6/main/IMAGE/IMAGE_a16de96f6d95f6b550cfe035801173cc_7cc6d3e70ce85877e76dd99ea7153780_cfc6cc61a395ce74e6ccaa5151dc6ea5.jpg",
    "type" : "image/jpeg",
    "bitrate" : 0,
    "duration" : 0,
    "title" : null,
    "properties" : null,
    "alternate" : [ {
      "href" : "https://i334.ntcdntempv3.com/data/images/12704/437739/024-fix.jpg?data=net",
      "type" : "image/jpeg",
      "bitrate" : 0,
      "duration" : 0,
      "title" : null,
      "properties" : null,
      "alternate" : null
    } ]
  }, {
    "href" : "https://raw.githubusercontent.com/duyhuynh652018/comic_storage6/main/IMAGE/IMAGE_a16de96f6d95f6b550cfe035801173cc_7cc6d3e70ce85877e76dd99ea7153780_a947c664195f579bd4fd52401350c28e.jpg",
    "type" : "image/jpeg",
    "bitrate" : 0,
    "duration" : 0,
    "title" : null,
    "properties" : null,
    "alternate" : [ {
      "href" : "https://i334.ntcdntempv3.com/data/images/12704/437739/025-fix.jpg?data=net",
      "type" : "image/jpeg",
      "bitrate" : 0,
      "duration" : 0,
      "title" : null,
      "properties" : null,
      "alternate" : null
    } ]
  }, {
    "href" : "https://raw.githubusercontent.com/duyhuynh652018/comic_storage6/main/IMAGE/IMAGE_a16de96f6d95f6b550cfe035801173cc_7cc6d3e70ce85877e76dd99ea7153780_b9b097244feadf97c49f719766a939da.jpg",
    "type" : "image/jpeg",
    "bitrate" : 0,
    "duration" : 0,
    "title" : null,
    "properties" : null,
    "alternate" : [ {
      "href" : "https://i334.ntcdntempv3.com/data/images/12704/437739/026-fix.jpg?data=net",
      "type" : "image/jpeg",
      "bitrate" : 0,
      "duration" : 0,
      "title" : null,
      "properties" : null,
      "alternate" : null
    } ]
  }, {
    "href" : "https://raw.githubusercontent.com/duyhuynh652018/comic_storage6/main/IMAGE/IMAGE_a16de96f6d95f6b550cfe035801173cc_7cc6d3e70ce85877e76dd99ea7153780_b94fedb1c1a09b6407cde56a62b9b611.jpg",
    "type" : "image/jpeg",
    "bitrate" : 0,
    "duration" : 0,
    "title" : null,
    "properties" : null,
    "alternate" : [ {
      "href" : "https://i334.ntcdntempv3.com/data/images/12704/437739/027-fix.jpg?data=net",
      "type" : "image/jpeg",
      "bitrate" : 0,
      "duration" : 0,
      "title" : null,
      "properties" : null,
      "alternate" : null
    } ]
  }, {
    "href" : "https://raw.githubusercontent.com/duyhuynh652018/comic_storage6/main/IMAGE/IMAGE_a16de96f6d95f6b550cfe035801173cc_7cc6d3e70ce85877e76dd99ea7153780_b309516b3d97cbb19ad544d2b738faf7.jpg",
    "type" : "image/jpeg",
    "bitrate" : 0,
    "duration" : 0,
    "title" : null,
    "properties" : null,
    "alternate" : [ {
      "href" : "https://i334.ntcdntempv3.com/data/images/12704/437739/028-fix.jpg?data=net",
      "type" : "image/jpeg",
      "bitrate" : 0,
      "duration" : 0,
      "title" : null,
      "properties" : null,
      "alternate" : null
    } ]
  }, {
    "href" : "https://raw.githubusercontent.com/duyhuynh652018/comic_storage6/main/IMAGE/IMAGE_a16de96f6d95f6b550cfe035801173cc_7cc6d3e70ce85877e76dd99ea7153780_18cc8fedaa8fec9e3c1553b36f0c91db.jpg",
    "type" : "image/jpeg",
    "bitrate" : 0,
    "duration" : 0,
    "title" : null,
    "properties" : null,
    "alternate" : [ {
      "href" : "https://i334.ntcdntempv3.com/data/images/12704/437739/029-fix.jpg?data=net",
      "type" : "image/jpeg",
      "bitrate" : 0,
      "duration" : 0,
      "title" : null,
      "properties" : null,
      "alternate" : null
    } ]
  }, {
    "href" : "https://raw.githubusercontent.com/duyhuynh652018/comic_storage6/main/IMAGE/IMAGE_a16de96f6d95f6b550cfe035801173cc_7cc6d3e70ce85877e76dd99ea7153780_ed5975df4e3842c1beedaaf3cea23ae0.jpg",
    "type" : "image/jpeg",
    "bitrate" : 0,
    "duration" : 0,
    "title" : null,
    "properties" : null,
    "alternate" : [ {
      "href" : "https://i334.ntcdntempv3.com/data/images/12704/437739/030-fix.jpg?data=net",
      "type" : "image/jpeg",
      "bitrate" : 0,
      "duration" : 0,
      "title" : null,
      "properties" : null,
      "alternate" : null
    } ]
  }, {
    "href" : "https://raw.githubusercontent.com/duyhuynh652018/comic_storage6/main/IMAGE/IMAGE_a16de96f6d95f6b550cfe035801173cc_7cc6d3e70ce85877e76dd99ea7153780_54739fa01d56ddbe765069e693ea5639.jpg",
    "type" : "image/jpeg",
    "bitrate" : 0,
    "duration" : 0,
    "title" : null,
    "properties" : null,
    "alternate" : [ {
      "href" : "https://i334.ntcdntempv3.com/data/images/12704/437739/031-fix.jpg?data=net",
      "type" : "image/jpeg",
      "bitrate" : 0,
      "duration" : 0,
      "title" : null,
      "properties" : null,
      "alternate" : null
    } ]
  }, {
    "href" : "https://raw.githubusercontent.com/duyhuynh652018/comic_storage6/main/IMAGE/IMAGE_a16de96f6d95f6b550cfe035801173cc_7cc6d3e70ce85877e76dd99ea7153780_a60f1c646132ff4b45f817b125ba2a40.jpg",
    "type" : "image/jpeg",
    "bitrate" : 0,
    "duration" : 0,
    "title" : null,
    "properties" : null,
    "alternate" : [ {
      "href" : "https://i334.ntcdntempv3.com/data/images/12704/437739/032-fix.jpg?data=net",
      "type" : "image/jpeg",
      "bitrate" : 0,
      "duration" : 0,
      "title" : null,
      "properties" : null,
      "alternate" : null
    } ]
  }, {
    "href" : "https://raw.githubusercontent.com/duyhuynh652018/comic_storage6/main/IMAGE/IMAGE_a16de96f6d95f6b550cfe035801173cc_7cc6d3e70ce85877e76dd99ea7153780_bd8fdae7ab31fee263caf42efc50565f.jpg",
    "type" : "image/jpeg",
    "bitrate" : 0,
    "duration" : 0,
    "title" : null,
    "properties" : null,
    "alternate" : [ {
      "href" : "https://i334.ntcdntempv3.com/data/images/12704/437739/033-fix.jpg?data=net",
      "type" : "image/jpeg",
      "bitrate" : 0,
      "duration" : 0,
      "title" : null,
      "properties" : null,
      "alternate" : null
    } ]
  }, {
    "href" : "https://raw.githubusercontent.com/duyhuynh652018/comic_storage6/main/IMAGE/IMAGE_a16de96f6d95f6b550cfe035801173cc_7cc6d3e70ce85877e76dd99ea7153780_36089d6e328befa56e2f427cdb959348.jpg",
    "type" : "image/jpeg",
    "bitrate" : 0,
    "duration" : 0,
    "title" : null,
    "properties" : null,
    "alternate" : [ {
      "href" : "https://i334.ntcdntempv3.com/data/images/12704/437739/034-fix.jpg?data=net",
      "type" : "image/jpeg",
      "bitrate" : 0,
      "duration" : 0,
      "title" : null,
      "properties" : null,
      "alternate" : null
    } ]
  }, {
    "href" : "https://raw.githubusercontent.com/duyhuynh652018/comic_storage6/main/IMAGE/IMAGE_a16de96f6d95f6b550cfe035801173cc_7cc6d3e70ce85877e76dd99ea7153780_d98393a7d290e8a8c467e97d2009936a.jpg",
    "type" : "image/jpeg",
    "bitrate" : 0,
    "duration" : 0,
    "title" : null,
    "properties" : null,
    "alternate" : [ {
      "href" : "https://i334.ntcdntempv3.com/data/images/12704/437739/035-fix.jpg?data=net",
      "type" : "image/jpeg",
      "bitrate" : 0,
      "duration" : 0,
      "title" : null,
      "properties" : null,
      "alternate" : null
    } ]
  }, {
    "href" : "https://raw.githubusercontent.com/duyhuynh652018/comic_storage6/main/IMAGE/IMAGE_a16de96f6d95f6b550cfe035801173cc_7cc6d3e70ce85877e76dd99ea7153780_1c7a745a693b955fae1d4642a6d0a059.jpg",
    "type" : "image/jpeg",
    "bitrate" : 0,
    "duration" : 0,
    "title" : null,
    "properties" : null,
    "alternate" : [ {
      "href" : "https://i334.ntcdntempv3.com/data/images/12704/437739/036-fix.jpg?data=net",
      "type" : "image/jpeg",
      "bitrate" : 0,
      "duration" : 0,
      "title" : null,
      "properties" : null,
      "alternate" : null
    } ]
  }, {
    "href" : "https://raw.githubusercontent.com/duyhuynh652018/comic_storage6/main/IMAGE/IMAGE_a16de96f6d95f6b550cfe035801173cc_7cc6d3e70ce85877e76dd99ea7153780_e56210a44e27bca5ad4f1d8b83882474.jpg",
    "type" : "image/jpeg",
    "bitrate" : 0,
    "duration" : 0,
    "title" : null,
    "properties" : null,
    "alternate" : [ {
      "href" : "https://i334.ntcdntempv3.com/data/images/12704/437739/037-fix.jpg?data=net",
      "type" : "image/jpeg",
      "bitrate" : 0,
      "duration" : 0,
      "title" : null,
      "properties" : null,
      "alternate" : null
    } ]
  }, {
    "href" : "https://raw.githubusercontent.com/duyhuynh652018/comic_storage6/main/IMAGE/IMAGE_a16de96f6d95f6b550cfe035801173cc_7cc6d3e70ce85877e76dd99ea7153780_959c1139ab10c4e53f911680c7e68718.jpg",
    "type" : "image/jpeg",
    "bitrate" : 0,
    "duration" : 0,
    "title" : null,
    "properties" : null,
    "alternate" : [ {
      "href" : "https://i334.ntcdntempv3.com/data/images/12704/437739/038-fix.jpg?data=net",
      "type" : "image/jpeg",
      "bitrate" : 0,
      "duration" : 0,
      "title" : null,
      "properties" : null,
      "alternate" : null
    } ]
  }, {
    "href" : "https://raw.githubusercontent.com/duyhuynh652018/comic_storage6/main/IMAGE/IMAGE_a16de96f6d95f6b550cfe035801173cc_7cc6d3e70ce85877e76dd99ea7153780_97c0a0b3b312a108a05d67b51769b6c2.jpg",
    "type" : "image/jpeg",
    "bitrate" : 0,
    "duration" : 0,
    "title" : null,
    "properties" : null,
    "alternate" : [ {
      "href" : "https://i334.ntcdntempv3.com/data/images/12704/437739/039-fix.jpg?data=net",
      "type" : "image/jpeg",
      "bitrate" : 0,
      "duration" : 0,
      "title" : null,
      "properties" : null,
      "alternate" : null
    } ]
  }, {
    "href" : "https://raw.githubusercontent.com/duyhuynh652018/comic_storage6/main/IMAGE/IMAGE_a16de96f6d95f6b550cfe035801173cc_7cc6d3e70ce85877e76dd99ea7153780_556821a5c2e617334474ab84b4ea1133.jpg",
    "type" : "image/jpeg",
    "bitrate" : 0,
    "duration" : 0,
    "title" : null,
    "properties" : null,
    "alternate" : [ {
      "href" : "https://i334.ntcdntempv3.com/data/images/12704/437739/040-fix.jpg?data=net",
      "type" : "image/jpeg",
      "bitrate" : 0,
      "duration" : 0,
      "title" : null,
      "properties" : null,
      "alternate" : null
    } ]
  }, {
    "href" : "https://raw.githubusercontent.com/duyhuynh652018/comic_storage6/main/IMAGE/IMAGE_a16de96f6d95f6b550cfe035801173cc_7cc6d3e70ce85877e76dd99ea7153780_b17b3146cb4d5837f3df413025f4d5a6.jpg",
    "type" : "image/jpeg",
    "bitrate" : 0,
    "duration" : 0,
    "title" : null,
    "properties" : null,
    "alternate" : [ {
      "href" : "https://i334.ntcdntempv3.com/data/images/12704/437739/041-fix.jpg?data=net",
      "type" : "image/jpeg",
      "bitrate" : 0,
      "duration" : 0,
      "title" : null,
      "properties" : null,
      "alternate" : null
    } ]
  }, {
    "href" : "https://raw.githubusercontent.com/duyhuynh652018/comic_storage6/main/IMAGE/IMAGE_a16de96f6d95f6b550cfe035801173cc_7cc6d3e70ce85877e76dd99ea7153780_3d926aae0ed44045dccd53a3c9efd9d2.jpg",
    "type" : "image/jpeg",
    "bitrate" : 0,
    "duration" : 0,
    "title" : null,
    "properties" : null,
    "alternate" : [ {
      "href" : "https://i334.ntcdntempv3.com/data/images/12704/437739/042-fix.jpg?data=net",
      "type" : "image/jpeg",
      "bitrate" : 0,
      "duration" : 0,
      "title" : null,
      "properties" : null,
      "alternate" : null
    } ]
  }, {
    "href" : "https://raw.githubusercontent.com/duyhuynh652018/comic_storage6/main/IMAGE/IMAGE_a16de96f6d95f6b550cfe035801173cc_7cc6d3e70ce85877e76dd99ea7153780_6e5adb32c642780e8365603ad8eb4bc6.jpg",
    "type" : "image/jpeg",
    "bitrate" : 0,
    "duration" : 0,
    "title" : null,
    "properties" : null,
    "alternate" : [ {
      "href" : "https://i334.ntcdntempv3.com/data/images/12704/437739/043-fix.jpg?data=net",
      "type" : "image/jpeg",
      "bitrate" : 0,
      "duration" : 0,
      "title" : null,
      "properties" : null,
      "alternate" : null
    } ]
  }, {
    "href" : "https://raw.githubusercontent.com/duyhuynh652018/comic_storage6/main/IMAGE/IMAGE_a16de96f6d95f6b550cfe035801173cc_7cc6d3e70ce85877e76dd99ea7153780_e3cb825130a15fde1169cc9c8564136b.jpg",
    "type" : "image/jpeg",
    "bitrate" : 0,
    "duration" : 0,
    "title" : null,
    "properties" : null,
    "alternate" : [ {
      "href" : "https://i334.ntcdntempv3.com/data/images/12704/437739/044-fix.jpg?data=net",
      "type" : "image/jpeg",
      "bitrate" : 0,
      "duration" : 0,
      "title" : null,
      "properties" : null,
      "alternate" : null
    } ]
  }, {
    "href" : "https://raw.githubusercontent.com/duyhuynh652018/comic_storage6/main/IMAGE/IMAGE_a16de96f6d95f6b550cfe035801173cc_7cc6d3e70ce85877e76dd99ea7153780_1454cc9530ae27f61f27b478a5a9e6ab.jpg",
    "type" : "image/jpeg",
    "bitrate" : 0,
    "duration" : 0,
    "title" : null,
    "properties" : null,
    "alternate" : [ {
      "href" : "https://i334.ntcdntempv3.com/data/images/12704/437739/045-fix.jpg?data=net",
      "type" : "image/jpeg",
      "bitrate" : 0,
      "duration" : 0,
      "title" : null,
      "properties" : null,
      "alternate" : null
    } ]
  } ],
  "toc" : null,
  "@context" : "https://readium.org/webpub-manifest/context.jsonld"
}